gooddata_pandas/__init__.py
gooddata_pandas/_version.py
gooddata_pandas/data_access.py
gooddata_pandas/dataframe.py
gooddata_pandas/good_pandas.py
gooddata_pandas/py.typed
gooddata_pandas/result_convertor.py
gooddata_pandas/series.py
gooddata_pandas/utils.py
gooddata_pandas-1.58.0.dist-info/METADATA
gooddata_pandas-1.58.0.dist-info/WHEEL
gooddata_pandas-1.58.0.dist-info/licenses/LICENSE.txt
gooddata_pandas-1.58.0.dist-info/RECORD
