Metadata-Version: 2.4
Name: gooddata-pandas
Version: 1.58.0
Summary: GoodData Cloud to pandas
Project-URL: Documentation, https://gooddata-pandas.readthedocs.io/en/v1.58.0
Project-URL: Source, https://github.com/gooddata/gooddata-python-sdk
Author-email: GoodData <support@gooddata.com>
License-Expression: MIT
License-File: LICENSE.txt
Keywords: analytics,business,cloud,data,data_frame,frame,gooddata,headless,headless-bi,intelligence,layer,metrics,native,pandas,semantic,series,sql
Classifier: Development Status :: 5 - Production/Stable
Classifier: Environment :: Console
Classifier: Programming Language :: Python :: 3.10
Classifier: Programming Language :: Python :: 3.11
Classifier: Programming Language :: Python :: 3.12
Classifier: Programming Language :: Python :: 3.13
Classifier: Programming Language :: Python :: 3.14
Classifier: Topic :: Database
Classifier: Topic :: Scientific/Engineering
Classifier: Topic :: Software Development
Classifier: Typing :: Typed
Requires-Python: >=3.10
Requires-Dist: gooddata-sdk~=1.58.0
Requires-Dist: pandas<3.0.0,>=2.0.0
